{"maxPage": 1919, "referenceId": "1703850", "summary": {"soType": 5, "productAttr": null, "productCommentSummary": {"poorCountStr": "100+", "averageScore": 5, "commentCount": 19000, "goodRate": 0.979, "goodCountStr": "1.8万+", "generalRateStyle": 2, "afterCount": 30, "poorRate": 0.01, "poorRateShow": 1, "goodRateShow": 98, "goodRateStyle": 146, "skuIds": null, "generalRateShow": 1, "generalRate": 0.011, "skuId": 1703850, "poorRateStyle": 2, "goodCount": 18000, "afterCountStr": "30+", "poorCount": 100, "commentCountStr": "1.9万+", "showCount": 2300, "generalCount": 200, "generalCountStr": "200+", "showCountStr": "2300+", "productId": 1703850}, "jwotestProduct": "99", "maxPage": 1919, "score": 0, "imageListCount": 500}}
{"maxPage": 9325, "referenceId": "1069486", "summary": {"soType": 5, "productAttr": null, "productCommentSummary": {"poorCountStr": "1500+", "averageScore": 5, "commentCount": 93000, "goodRate": 0.962, "goodCountStr": "8.9万+", "generalRateStyle": 3, "afterCount": 100, "poorRate": 0.017, "poorRateShow": 2, "goodRateShow": 96, "goodRateStyle": 144, "skuIds": null, "generalRateShow": 2, "generalRate": 0.021, "skuId": 1069486, "poorRateStyle": 3, "goodCount": 89000, "afterCountStr": "100+", "poorCount": 1500, "commentCountStr": "9.3万+", "showCount": 8200, "generalCount": 2000, "generalCountStr": "2000+", "showCountStr": "8200+", "productId": 1069486}, "jwotestProduct": "99", "maxPage": 9325, "score": 0, "imageListCount": 500}}
{"maxPage": 2564, "referenceId": "1773994", "summary": {"soType": 5, "productAttr": null, "productCommentSummary": {"poorCountStr": "400+", "averageScore": 5, "commentCount": 25000, "goodRate": 0.963, "goodCountStr": "2.4万+", "generalRateStyle": 3, "afterCount": 100, "poorRate": 0.019, "poorRateShow": 2, "goodRateShow": 96, "goodRateStyle": 144, "skuIds": null, "generalRateShow": 2, "generalRate": 0.018, "skuId": 1773994, "poorRateStyle": 3, "goodCount": 24000, "afterCountStr": "100+", "poorCount": 400, "commentCountStr": "2.5万+", "showCount": 6600, "generalCount": 400, "generalCountStr": "400+", "showCountStr": "6600+", "productId": 1773994}, "jwotestProduct": "99", "maxPage": 2564, "score": 0, "imageListCount": 500}}
{"maxPage": 2126, "referenceId": "2718250", "summary": {"soType": 5, "productAttr": null, "productCommentSummary": {"poorCountStr": "300+", "averageScore": 5, "commentCount": 21000, "goodRate": 0.968, "goodCountStr": "2万+", "generalRateStyle": 3, "afterCount": 100, "poorRate": 0.014, "poorRateShow": 1, "goodRateShow": 97, "goodRateStyle": 145, "skuIds": null, "generalRateShow": 2, "generalRate": 0.018, "skuId": 2718250, "poorRateStyle": 2, "goodCount": 20000, "afterCountStr": "100+", "poorCount": 300, "commentCountStr": "2.1万+", "showCount": 2800, "generalCount": 300, "generalCountStr": "300+", "showCountStr": "2800+", "productId": 2718250}, "jwotestProduct": "99", "maxPage": 2126, "score": 0, "imageListCount": 500}}
{"maxPage": 2881, "referenceId": "2984344", "summary": {"soType": 5, "productAttr": null, "productCommentSummary": {"poorCountStr": "500+", "averageScore": 5, "commentCount": 28000, "goodRate": 0.964, "goodCountStr": "2.7万+", "generalRateStyle": 3, "afterCount": 200, "poorRate": 0.017, "poorRateShow": 2, "goodRateShow": 96, "goodRateStyle": 144, "skuIds": null, "generalRateShow": 2, "generalRate": 0.019, "skuId": 2984344, "poorRateStyle": 3, "goodCount": 27000, "afterCountStr": "200+", "poorCount": 500, "commentCountStr": "2.8万+", "showCount": 10000, "generalCount": 500, "generalCountStr": "500+", "showCountStr": "1万+", "productId": 2984344}, "jwotestProduct": "99", "maxPage": 2881, "score": 0, "imageListCount": 500}}
{"maxPage": 780, "referenceId": "3130047", "summary": {"soType": 5, "productAttr": null, "productCommentSummary": {"poorCountStr": "100+", "averageScore": 5, "commentCount": 7700, "goodRate": 0.966, "goodCountStr": "7500+", "generalRateStyle": 2, "afterCount": 20, "poorRate": 0.018, "poorRateShow": 2, "goodRateShow": 96, "goodRateStyle": 145, "skuIds": null, "generalRateShow": 2, "generalRate": 0.016, "skuId": 3130047, "poorRateStyle": 3, "goodCount": 7500, "afterCountStr": "20+", "poorCount": 100, "commentCountStr": "7700+", "showCount": 3800, "generalCount": 100, "generalCountStr": "100+", "showCountStr": "3800+", "productId": 3130047}, "jwotestProduct": "99", "maxPage": 780, "score": 0, "imageListCount": 500}}
{"maxPage": 1767, "referenceId": "2833247", "summary": {"soType": 5, "productAttr": null, "productCommentSummary": {"poorCountStr": "300+", "averageScore": 5, "commentCount": 17000, "goodRate": 0.967, "goodCountStr": "1.7万+", "generalRateStyle": 2, "afterCount": 100, "poorRate": 0.018, "poorRateShow": 2, "goodRateShow": 96, "goodRateStyle": 145, "skuIds": null, "generalRateShow": 2, "generalRate": 0.015, "skuId": 2833247, "poorRateStyle": 3, "goodCount": 17000, "afterCountStr": "100+", "poorCount": 300, "commentCountStr": "1.7万+", "showCount": 6700, "generalCount": 200, "generalCountStr": "200+", "showCountStr": "6700+", "productId": 2833247}, "jwotestProduct": "99", "maxPage": 1767, "score": 0, "imageListCount": 500}}
{"maxPage": 1314, "referenceId": "2833305", "summary": {"soType": 5, "productAttr": null, "productCommentSummary": {"poorCountStr": "200+", "averageScore": 5, "commentCount": 13000, "goodRate": 0.969, "goodCountStr": "1.2万+", "generalRateStyle": 2, "afterCount": 100, "poorRate": 0.016, "poorRateShow": 2, "goodRateShow": 96, "goodRateStyle": 146, "skuIds": null, "generalRateShow": 2, "generalRate": 0.015, "skuId": 2833305, "poorRateStyle": 2, "goodCount": 12000, "afterCountStr": "100+", "poorCount": 200, "commentCountStr": "1.3万+", "showCount": 5200, "generalCount": 200, "generalCountStr": "200+", "showCountStr": "5200+", "productId": 2833305}, "jwotestProduct": "99", "maxPage": 1314, "score": 0, "imageListCount": 500}}
{"maxPage": 4471, "referenceId": "1703852", "summary": {"soType": 5, "productAttr": null, "productCommentSummary": {"poorCountStr": "500+", "averageScore": 5, "commentCount": 44000, "goodRate": 0.968, "goodCountStr": "4.3万+", "generalRateStyle": 3, "afterCount": 100, "poorRate": 0.012, "poorRateShow": 1, "goodRateShow": 97, "goodRateStyle": 145, "skuIds": null, "generalRateShow": 2, "generalRate": 0.02, "skuId": 1703852, "poorRateStyle": 2, "goodCount": 43000, "afterCountStr": "100+", "poorCount": 500, "commentCountStr": "4.4万+", "showCount": 5000, "generalCount": 900, "generalCountStr": "900+", "showCountStr": "5000+", "productId": 1703852}, "jwotestProduct": "99", "maxPage": 4471, "score": 0, "imageListCount": 500}}
{"maxPage": 2343, "referenceId": "1887641", "summary": {"soType": 5, "productAttr": null, "productCommentSummary": {"poorCountStr": "400+", "averageScore": 5, "commentCount": 23000, "goodRate": 0.961, "goodCountStr": "2.2万+", "generalRateStyle": 3, "afterCount": 70, "poorRate": 0.018, "poorRateShow": 2, "goodRateShow": 96, "goodRateStyle": 144, "skuIds": null, "generalRateShow": 2, "generalRate": 0.021, "skuId": 1887641, "poorRateStyle": 3, "goodCount": 22000, "afterCountStr": "70+", "poorCount": 400, "commentCountStr": "2.3万+", "showCount": 6000, "generalCount": 500, "generalCountStr": "500+", "showCountStr": "6000+", "productId": 1887641}, "jwotestProduct": "99", "maxPage": 2343, "score": 0, "imageListCount": 500}}
{"maxPage": 1464, "referenceId": "1665416", "summary": {"soType": 5, "productAttr": null, "productCommentSummary": {"poorCountStr": "300+", "averageScore": 5, "commentCount": 14000, "goodRate": 0.962, "goodCountStr": "1.4万+", "generalRateStyle": 3, "afterCount": 60, "poorRate": 0.02, "poorRateShow": 2, "goodRateShow": 96, "goodRateStyle": 144, "skuIds": null, "generalRateShow": 2, "generalRate": 0.018, "skuId": 1665416, "poorRateStyle": 3, "goodCount": 14000, "afterCountStr": "60+", "poorCount": 300, "commentCountStr": "1.4万+", "showCount": 4400, "generalCount": 200, "generalCountStr": "200+", "showCountStr": "4400+", "productId": 1665416}, "jwotestProduct": "99", "maxPage": 1464, "score": 0, "imageListCount": 500}}
{"maxPage": 892, "referenceId": "3195185", "summary": {"soType": 5, "productAttr": null, "productCommentSummary": {"poorCountStr": "100+", "averageScore": 5, "commentCount": 8900, "goodRate": 0.974, "goodCountStr": "8600+", "generalRateStyle": 2, "afterCount": 10, "poorRate": 0.014, "poorRateShow": 1, "goodRateShow": 98, "goodRateStyle": 146, "skuIds": null, "generalRateShow": 1, "generalRate": 0.012, "skuId": 3195185, "poorRateStyle": 2, "goodCount": 8600, "afterCountStr": "10+", "poorCount": 100, "commentCountStr": "8900+", "showCount": 4600, "generalCount": 100, "generalCountStr": "100+", "showCountStr": "4600+", "productId": 3195185}, "jwotestProduct": "99", "maxPage": 892, "score": 0, "imageListCount": 500}}
{"maxPage": 475, "referenceId": "2426559", "summary": {"soType": 5, "productAttr": null, "productCommentSummary": {"poorCountStr": "40+", "averageScore": 5, "commentCount": 4700, "goodRate": 0.982, "goodCountStr": "4600+", "generalRateStyle": 1, "afterCount": 100, "poorRate": 0.009, "poorRateShow": 1, "goodRateShow": 98, "goodRateStyle": 148, "skuIds": null, "generalRateShow": 1, "generalRate": 0.009, "skuId": 2426559, "poorRateStyle": 1, "goodCount": 4600, "afterCountStr": "100+", "poorCount": 40, "commentCountStr": "4700+", "showCount": 3200, "generalCount": 40, "generalCountStr": "40+", "showCountStr": "3200+", "productId": 2426559}, "jwotestProduct": "99", "maxPage": 475, "score": 0, "imageListCount": 500}}
{"maxPage": 830, "referenceId": "2985080", "summary": {"soType": 5, "productAttr": null, "productCommentSummary": {"poorCountStr": "100+", "averageScore": 5, "commentCount": 8200, "goodRate": 0.967, "goodCountStr": "8000+", "generalRateStyle": 2, "afterCount": 20, "poorRate": 0.017, "poorRateShow": 2, "goodRateShow": 96, "goodRateStyle": 145, "skuIds": null, "generalRateShow": 2, "generalRate": 0.016, "skuId": 2985080, "poorRateStyle": 3, "goodCount": 8000, "afterCountStr": "20+", "poorCount": 100, "commentCountStr": "8200+", "showCount": 3400, "generalCount": 100, "generalCountStr": "100+", "showCountStr": "3400+", "productId": 2985080}, "jwotestProduct": "99", "maxPage": 830, "score": 0, "imageListCount": 500}}
{"maxPage": 526, "referenceId": "2363563", "summary": {"soType": 5, "productAttr": null, "productCommentSummary": {"poorCountStr": "100+", "averageScore": 5, "commentCount": 5200, "goodRate": 0.961, "goodCountStr": "5000+", "generalRateStyle": 3, "afterCount": 10, "poorRate": 0.019, "poorRateShow": 2, "goodRateShow": 96, "goodRateStyle": 144, "skuIds": null, "generalRateShow": 2, "generalRate": 0.02, "skuId": 2363563, "poorRateStyle": 3, "goodCount": 5000, "afterCountStr": "10+", "poorCount": 100, "commentCountStr": "5200+", "showCount": 1800, "generalCount": 100, "generalCountStr": "100+", "showCountStr": "1800+", "productId": 2363563}, "jwotestProduct": "99", "maxPage": 526, "score": 0, "imageListCount": 500}}
{"maxPage": 1484, "referenceId": "1546449", "summary": {"soType": 5, "productAttr": null, "productCommentSummary": {"poorCountStr": "200+", "averageScore": 5, "commentCount": 14000, "goodRate": 0.969, "goodCountStr": "1.4万+", "generalRateStyle": 3, "afterCount": 20, "poorRate": 0.013, "poorRateShow": 1, "goodRateShow": 97, "goodRateStyle": 145, "skuIds": null, "generalRateShow": 2, "generalRate": 0.018, "skuId": 1546449, "poorRateStyle": 2, "goodCount": 14000, "afterCountStr": "20+", "poorCount": 200, "commentCountStr": "1.4万+", "showCount": 2300, "generalCount": 200, "generalCountStr": "200+", "showCountStr": "2300+", "productId": 1546449}, "jwotestProduct": "99", "maxPage": 1484, "score": 0, "imageListCount": 500}}
{"maxPage": 2314, "referenceId": "2670443", "summary": {"soType": 5, "productAttr": null, "productCommentSummary": {"poorCountStr": "400+", "averageScore": 5, "commentCount": 23000, "goodRate": 0.964, "goodCountStr": "2.2万+", "generalRateStyle": 3, "afterCount": 40, "poorRate": 0.017, "poorRateShow": 2, "goodRateShow": 96, "goodRateStyle": 144, "skuIds": null, "generalRateShow": 2, "generalRate": 0.019, "skuId": 2670443, "poorRateStyle": 3, "goodCount": 22000, "afterCountStr": "40+", "poorCount": 400, "commentCountStr": "2.3万+", "showCount": 3500, "generalCount": 400, "generalCountStr": "400+", "showCountStr": "3500+", "productId": 2670443}, "jwotestProduct": "99", "maxPage": 2314, "score": 0, "imageListCount": 500}}
{"maxPage": 5790, "referenceId": "1069488", "summary": {"soType": 5, "productAttr": null, "productCommentSummary": {"poorCountStr": "700+", "averageScore": 5, "commentCount": 57000, "goodRate": 0.972, "goodCountStr": "5.6万+", "generalRateStyle": 2, "afterCount": 90, "poorRate": 0.012, "poorRateShow": 1, "goodRateShow": 97, "goodRateStyle": 146, "skuIds": null, "generalRateShow": 2, "generalRate": 0.016, "skuId": 1069488, "poorRateStyle": 2, "goodCount": 56000, "afterCountStr": "90+", "poorCount": 700, "commentCountStr": "5.7万+", "showCount": 4900, "generalCount": 900, "generalCountStr": "900+", "showCountStr": "4900+", "productId": 1069488}, "jwotestProduct": "99", "maxPage": 5790, "score": 0, "imageListCount": 500}}
{"maxPage": 336, "referenceId": "2833719", "summary": {"soType": 5, "productAttr": null, "productCommentSummary": {"poorCountStr": "50+", "averageScore": 5, "commentCount": 3300, "goodRate": 0.968, "goodCountStr": "3200+", "generalRateStyle": 2, "afterCount": 10, "poorRate": 0.016, "poorRateShow": 2, "goodRateShow": 96, "goodRateStyle": 146, "skuIds": null, "generalRateShow": 2, "generalRate": 0.016, "skuId": 2833719, "poorRateStyle": 2, "goodCount": 3200, "afterCountStr": "10+", "poorCount": 50, "commentCountStr": "3300+", "showCount": 600, "generalCount": 50, "generalCountStr": "50+", "showCountStr": "600+", "productId": 2833719}, "jwotestProduct": "99", "maxPage": 336, "score": 0, "imageListCount": 500}}
{"maxPage": 1172, "referenceId": "2718238", "summary": {"soType": 5, "productAttr": null, "productCommentSummary": {"poorCountStr": "100+", "averageScore": 5, "commentCount": 11000, "goodRate": 0.965, "goodCountStr": "1.1万+", "generalRateStyle": 3, "afterCount": 70, "poorRate": 0.016, "poorRateShow": 2, "goodRateShow": 96, "goodRateStyle": 145, "skuIds": null, "generalRateShow": 2, "generalRate": 0.019, "skuId": 2718238, "poorRateStyle": 2, "goodCount": 11000, "afterCountStr": "70+", "poorCount": 100, "commentCountStr": "1.1万+", "showCount": 1600, "generalCount": 200, "generalCountStr": "200+", "showCountStr": "1600+", "productId": 2718238}, "jwotestProduct": "99", "maxPage": 1172, "score": 0, "imageListCount": 500}}
{"maxPage": 315, "referenceId": "2833309", "summary": {"soType": 5, "productAttr": null, "productCommentSummary": {"poorCountStr": "50+", "averageScore": 5, "commentCount": 3100, "goodRate": 0.969, "goodCountStr": "3000+", "generalRateStyle": 2, "afterCount": 10, "poorRate": 0.015, "poorRateShow": 2, "goodRateShow": 96, "goodRateStyle": 146, "skuIds": null, "generalRateShow": 2, "generalRate": 0.016, "skuId": 2833309, "poorRateStyle": 2, "goodCount": 3000, "afterCountStr": "10", "poorCount": 50, "commentCountStr": "3100+", "showCount": 500, "generalCount": 50, "generalCountStr": "50+", "showCountStr": "500+", "productId": 2833309}, "jwotestProduct": "99", "maxPage": 315, "score": 0, "imageListCount": 500}}
{"maxPage": 242, "referenceId": "2425414", "summary": {"soType": 5, "productAttr": null, "productCommentSummary": {"poorCountStr": "20+", "averageScore": 5, "commentCount": 2400, "goodRate": 0.983, "goodCountStr": "2300+", "generalRateStyle": 1, "afterCount": 30, "poorRate": 0.009, "poorRateShow": 1, "goodRateShow": 98, "goodRateStyle": 148, "skuIds": null, "generalRateShow": 1, "generalRate": 0.008, "skuId": 2425414, "poorRateStyle": 1, "goodCount": 2300, "afterCountStr": "30+", "poorCount": 20, "commentCountStr": "2400+", "showCount": 1600, "generalCount": 20, "generalCountStr": "20+", "showCountStr": "1600+", "productId": 2425414}, "jwotestProduct": "99", "maxPage": 242, "score": 0, "imageListCount": 500}}
{"maxPage": 846, "referenceId": "1774012", "summary": {"soType": 5, "productAttr": null, "productCommentSummary": {"poorCountStr": "100+", "averageScore": 5, "commentCount": 8400, "goodRate": 0.964, "goodCountStr": "8100+", "generalRateStyle": 3, "afterCount": 2, "poorRate": 0.017, "poorRateShow": 2, "goodRateShow": 96, "goodRateStyle": 144, "skuIds": null, "generalRateShow": 2, "generalRate": 0.019, "skuId": 1774012, "poorRateStyle": 3, "goodCount": 8100, "afterCountStr": "2", "poorCount": 100, "commentCountStr": "8400+", "showCount": 2200, "generalCount": 100, "generalCountStr": "100+", "showCountStr": "2200+", "productId": 1774012}, "jwotestProduct": "99", "maxPage": 846, "score": 0, "imageListCount": 500}}
{"maxPage": 553, "referenceId": "1703865", "summary": {"soType": 5, "productAttr": null, "productCommentSummary": {"poorCountStr": "70+", "averageScore": 5, "commentCount": 5500, "goodRate": 0.97, "goodCountStr": "5300+", "generalRateStyle": 2, "afterCount": 10, "poorRate": 0.014, "poorRateShow": 1, "goodRateShow": 97, "goodRateStyle": 146, "skuIds": null, "generalRateShow": 2, "generalRate": 0.016, "skuId": 1703865, "poorRateStyle": 2, "goodCount": 5300, "afterCountStr": "10", "poorCount": 70, "commentCountStr": "5500+", "showCount": 1000, "generalCount": 90, "generalCountStr": "90+", "showCountStr": "1000+", "productId": 1703865}, "jwotestProduct": "99", "maxPage": 553, "score": 0, "imageListCount": 500}}
{"maxPage": 138, "referenceId": "3560448", "summary": {"soType": 5, "productAttr": null, "productCommentSummary": {"poorCountStr": "30+", "averageScore": 5, "commentCount": 1300, "goodRate": 0.951, "goodCountStr": "1300+", "generalRateStyle": 4, "afterCount": 20, "poorRate": 0.023, "poorRateShow": 2, "goodRateShow": 95, "goodRateStyle": 143, "skuIds": null, "generalRateShow": 3, "generalRate": 0.026, "skuId": 3560448, "poorRateStyle": 3, "goodCount": 1300, "afterCountStr": "20+", "poorCount": 30, "commentCountStr": "1300+", "showCount": 200, "generalCount": 30, "generalCountStr": "30+", "showCountStr": "200+", "productId": 3560448}, "jwotestProduct": "99", "maxPage": 138, "score": 0, "imageListCount": 419}}
{"maxPage": 1546, "referenceId": "1546456", "summary": {"soType": 5, "productAttr": null, "productCommentSummary": {"poorCountStr": "200+", "averageScore": 5, "commentCount": 15000, "goodRate": 0.965, "goodCountStr": "1.4万+", "generalRateStyle": 3, "afterCount": 20, "poorRate": 0.015, "poorRateShow": 2, "goodRateShow": 96, "goodRateStyle": 145, "skuIds": null, "generalRateShow": 2, "generalRate": 0.02, "skuId": 1546456, "poorRateStyle": 2, "goodCount": 14000, "afterCountStr": "20+", "poorCount": 200, "commentCountStr": "1.5万+", "showCount": 2100, "generalCount": 300, "generalCountStr": "300+", "showCountStr": "2100+", "productId": 1546456}, "jwotestProduct": "99", "maxPage": 1546, "score": 0, "imageListCount": 500}}
{"maxPage": 474, "referenceId": "3761659", "summary": {"soType": 5, "productAttr": null, "productCommentSummary": {"poorCountStr": "30+", "averageScore": 5, "commentCount": 4700, "goodRate": 0.986, "goodCountStr": "4600+", "generalRateStyle": 1, "afterCount": 100, "poorRate": 0.008, "poorRateShow": 1, "goodRateShow": 98, "goodRateStyle": 148, "skuIds": null, "generalRateShow": 1, "generalRate": 0.006, "skuId": 3761659, "poorRateStyle": 1, "goodCount": 4600, "afterCountStr": "100+", "poorCount": 30, "commentCountStr": "4700+", "showCount": 2600, "generalCount": 30, "generalCountStr": "30+", "showCountStr": "2600+", "productId": 3761659}, "jwotestProduct": "99", "maxPage": 474, "score": 0, "imageListCount": 500}}
{"maxPage": 91, "referenceId": "3819580", "summary": {"soType": 5, "productAttr": null, "productCommentSummary": {"poorCountStr": "20+", "averageScore": 5, "commentCount": 900, "goodRate": 0.959, "goodCountStr": "800+", "generalRateStyle": 3, "afterCount": 30, "poorRate": 0.022, "poorRateShow": 2, "goodRateShow": 96, "goodRateStyle": 144, "skuIds": null, "generalRateShow": 2, "generalRate": 0.019, "skuId": 3819580, "poorRateStyle": 3, "goodCount": 800, "afterCountStr": "30+", "poorCount": 20, "commentCountStr": "900+", "showCount": 400, "generalCount": 10, "generalCountStr": "10+", "showCountStr": "400+", "productId": 3819580}, "jwotestProduct": "99", "maxPage": 91, "score": 0, "imageListCount": 500}}
{"maxPage": 586, "referenceId": "1703866", "summary": {"soType": 5, "productAttr": null, "productCommentSummary": {"poorCountStr": "100+", "averageScore": 5, "commentCount": 5800, "goodRate": 0.961, "goodCountStr": "5600+", "generalRateStyle": 3, "afterCount": 2, "poorRate": 0.017, "poorRateShow": 2, "goodRateShow": 96, "goodRateStyle": 144, "skuIds": null, "generalRateShow": 2, "generalRate": 0.022, "skuId": 1703866, "poorRateStyle": 3, "goodCount": 5600, "afterCountStr": "2", "poorCount": 100, "commentCountStr": "5800+", "showCount": 600, "generalCount": 100, "generalCountStr": "100+", "showCountStr": "600+", "productId": 1703866}, "jwotestProduct": "99", "maxPage": 586, "score": 0, "imageListCount": 500}}
{"maxPage": 178, "referenceId": "2985048", "summary": {"soType": 5, "productAttr": null, "productCommentSummary": {"poorCountStr": "20+", "averageScore": 5, "commentCount": 1700, "goodRate": 0.971, "goodCountStr": "1700+", "generalRateStyle": 2, "afterCount": 30, "poorRate": 0.015, "poorRateShow": 2, "goodRateShow": 97, "goodRateStyle": 146, "skuIds": null, "generalRateShow": 1, "generalRate": 0.014, "skuId": 2985048, "poorRateStyle": 2, "goodCount": 1700, "afterCountStr": "30+", "poorCount": 20, "commentCountStr": "1700+", "showCount": 900, "generalCount": 20, "generalCountStr": "20+", "showCountStr": "900+", "productId": 2985048}, "jwotestProduct": "99", "maxPage": 178, "score": 0, "imageListCount": 500}}
{"maxPage": 308, "referenceId": "1546440", "summary": {"soType": 5, "productAttr": null, "productCommentSummary": {"poorCountStr": "60+", "averageScore": 5, "commentCount": 3000, "goodRate": 0.964, "goodCountStr": "2900+", "generalRateStyle": 2, "afterCount": 5, "poorRate": 0.022, "poorRateShow": 2, "goodRateShow": 97, "goodRateStyle": 145, "skuIds": null, "generalRateShow": 1, "generalRate": 0.014, "skuId": 1546440, "poorRateStyle": 3, "goodCount": 2900, "afterCountStr": "5", "poorCount": 60, "commentCountStr": "3000+", "showCount": 600, "generalCount": 40, "generalCountStr": "40+", "showCountStr": "600+", "productId": 1546440}, "jwotestProduct": "99", "maxPage": 308, "score": 0, "imageListCount": 500}}
{"maxPage": 73, "referenceId": "3819510", "summary": {"soType": 5, "productAttr": null, "productCommentSummary": {"poorCountStr": "8", "averageScore": 5, "commentCount": 700, "goodRate": 0.978, "goodCountStr": "700+", "generalRateStyle": 2, "afterCount": 10, "poorRate": 0.01, "poorRateShow": 1, "goodRateShow": 98, "goodRateStyle": 146, "skuIds": null, "generalRateShow": 1, "generalRate": 0.012, "skuId": 3819510, "poorRateStyle": 2, "goodCount": 700, "afterCountStr": "10+", "poorCount": 8, "commentCountStr": "700+", "showCount": 300, "generalCount": 9, "generalCountStr": "9", "showCountStr": "300+", "productId": 3819510}, "jwotestProduct": "99", "maxPage": 73, "score": 0, "imageListCount": 500}}
{"maxPage": 202, "referenceId": "3037563", "summary": {"soType": 5, "productAttr": null, "productCommentSummary": {"poorCountStr": "20+", "averageScore": 5, "commentCount": 2000, "goodRate": 0.972, "goodCountStr": "1900+", "generalRateStyle": 2, "afterCount": 1, "poorRate": 0.013, "poorRateShow": 1, "goodRateShow": 97, "goodRateStyle": 146, "skuIds": null, "generalRateShow": 2, "generalRate": 0.015, "skuId": 3037563, "poorRateStyle": 2, "goodCount": 1900, "afterCountStr": "1", "poorCount": 20, "commentCountStr": "2000+", "showCount": 300, "generalCount": 30, "generalCountStr": "30+", "showCountStr": "300+", "productId": 3037563}, "jwotestProduct": "99", "maxPage": 202, "score": 0, "imageListCount": 500}}
{"maxPage": 368, "referenceId": "2322960", "summary": {"soType": 5, "productAttr": null, "productCommentSummary": {"poorCountStr": "40+", "averageScore": 5, "commentCount": 3600, "goodRate": 0.967, "goodCountStr": "3500+", "generalRateStyle": 3, "afterCount": 20, "poorRate": 0.012, "poorRateShow": 1, "goodRateShow": 97, "goodRateStyle": 145, "skuIds": null, "generalRateShow": 2, "generalRate": 0.021, "skuId": 2322960, "poorRateStyle": 2, "goodCount": 3500, "afterCountStr": "20+", "poorCount": 40, "commentCountStr": "3600+", "showCount": 400, "generalCount": 70, "generalCountStr": "70+", "showCountStr": "400+", "productId": 2322960}, "jwotestProduct": "99", "maxPage": 368, "score": 0, "imageListCount": 500}}
{"maxPage": 17, "referenceId": "4358112", "summary": {"soType": 5, "productAttr": null, "productCommentSummary": {"poorCountStr": "4", "averageScore": 5, "commentCount": 100, "goodRate": 0.964, "goodCountStr": "100+", "generalRateStyle": 2, "afterCount": 4, "poorRate": 0.024, "poorRateShow": 2, "goodRateShow": 97, "goodRateStyle": 144, "skuIds": null, "generalRateShow": 1, "generalRate": 0.012, "skuId": 4358112, "poorRateStyle": 4, "goodCount": 100, "afterCountStr": "4", "poorCount": 4, "commentCountStr": "100+", "showCount": 60, "generalCount": 2, "generalCountStr": "2", "showCountStr": "60+", "productId": 4358112}, "jwotestProduct": "99", "maxPage": 17, "score": 0, "imageListCount": 159}}
{"maxPage": 26, "referenceId": "3130033", "summary": {"soType": 5, "productAttr": null, "productCommentSummary": {"poorCountStr": "1", "averageScore": 5, "commentCount": 200, "goodRate": 0.986, "goodCountStr": "200+", "generalRateStyle": 2, "afterCount": 5, "poorRate": 0.003, "poorRateShow": 0, "goodRateShow": 99, "goodRateStyle": 148, "skuIds": null, "generalRateShow": 1, "generalRate": 0.011, "skuId": 3130033, "poorRateStyle": 0, "goodCount": 200, "afterCountStr": "5", "poorCount": 1, "commentCountStr": "200+", "showCount": 100, "generalCount": 3, "generalCountStr": "3", "showCountStr": "100+", "productId": 3130033}, "jwotestProduct": "99", "maxPage": 26, "score": 0, "imageListCount": 400}}
{"maxPage": 430, "referenceId": "1665421", "summary": {"soType": 5, "productAttr": null, "productCommentSummary": {"poorCountStr": "90+", "averageScore": 5, "commentCount": 4200, "goodRate": 0.959, "goodCountStr": "4100+", "generalRateStyle": 3, "afterCount": 10, "poorRate": 0.022, "poorRateShow": 2, "goodRateShow": 96, "goodRateStyle": 144, "skuIds": null, "generalRateShow": 2, "generalRate": 0.019, "skuId": 1665421, "poorRateStyle": 3, "goodCount": 4100, "afterCountStr": "10+", "poorCount": 90, "commentCountStr": "4200+", "showCount": 1200, "generalCount": 80, "generalCountStr": "80+", "showCountStr": "1200+", "productId": 1665421}, "jwotestProduct": "99", "maxPage": 430, "score": 0, "imageListCount": 500}}
{"maxPage": 164, "referenceId": "1703840", "summary": {"soType": 5, "productAttr": null, "productCommentSummary": {"poorCountStr": "30+", "averageScore": 5, "commentCount": 1600, "goodRate": 0.96, "goodCountStr": "1500+", "generalRateStyle": 3, "afterCount": 2, "poorRate": 0.021, "poorRateShow": 2, "goodRateShow": 96, "goodRateStyle": 144, "skuIds": null, "generalRateShow": 2, "generalRate": 0.019, "skuId": 1703840, "poorRateStyle": 3, "goodCount": 1500, "afterCountStr": "2", "poorCount": 30, "commentCountStr": "1600+", "showCount": 300, "generalCount": 30, "generalCountStr": "30+", "showCountStr": "300+", "productId": 1703840}, "jwotestProduct": "99", "maxPage": 164, "score": 0, "imageListCount": 500}}
{"maxPage": 51, "referenceId": "2426551", "summary": {"soType": 5, "productAttr": null, "productCommentSummary": {"poorCountStr": "6", "averageScore": 5, "commentCount": 500, "goodRate": 0.982, "goodCountStr": "400+", "generalRateStyle": 1, "afterCount": 7, "poorRate": 0.011, "poorRateShow": 1, "goodRateShow": 98, "goodRateStyle": 147, "skuIds": null, "generalRateShow": 1, "generalRate": 0.007, "skuId": 2426551, "poorRateStyle": 2, "goodCount": 400, "afterCountStr": "7", "poorCount": 6, "commentCountStr": "500+", "showCount": 200, "generalCount": 4, "generalCountStr": "4", "showCountStr": "200+", "productId": 2426551}, "jwotestProduct": "99", "maxPage": 51, "score": 0, "imageListCount": 500}}
{"maxPage": 3, "referenceId": "3655643", "summary": {"soType": 5, "productAttr": null, "productCommentSummary": {"poorCountStr": "0", "averageScore": 5, "commentCount": 20, "goodRate": 1.0, "goodCountStr": "20+", "generalRateStyle": 0, "afterCount": 2, "poorRate": 0.0, "poorRateShow": 0, "goodRateShow": 100, "goodRateStyle": 150, "skuIds": null, "generalRateShow": 0, "generalRate": 0.0, "skuId": 3655643, "poorRateStyle": 0, "goodCount": 20, "afterCountStr": "2", "poorCount": 0, "commentCountStr": "20+", "showCount": 20, "generalCount": 0, "generalCountStr": "0", "showCountStr": "20+", "productId": 3655643}, "jwotestProduct": "99", "maxPage": 3, "score": 0, "imageListCount": 84}}
{"maxPage": 71, "referenceId": "2363555", "summary": {"soType": 5, "productAttr": null, "productCommentSummary": {"poorCountStr": "10+", "averageScore": 5, "commentCount": 700, "goodRate": 0.954, "goodCountStr": "600+", "generalRateStyle": 3, "afterCount": 7, "poorRate": 0.025, "poorRateShow": 3, "goodRateShow": 95, "goodRateStyle": 143, "skuIds": null, "generalRateShow": 2, "generalRate": 0.021, "skuId": 2363555, "poorRateStyle": 4, "goodCount": 600, "afterCountStr": "7", "poorCount": 10, "commentCountStr": "700+", "showCount": 100, "generalCount": 10, "generalCountStr": "10+", "showCountStr": "100+", "productId": 2363555}, "jwotestProduct": "99", "maxPage": 71, "score": 0, "imageListCount": 172}}
{"maxPage": 32, "referenceId": "2985018", "summary": {"soType": 5, "productAttr": null, "productCommentSummary": {"poorCountStr": "3", "averageScore": 5, "commentCount": 300, "goodRate": 0.979, "goodCountStr": "300+", "generalRateStyle": 2, "afterCount": 7, "poorRate": 0.009, "poorRateShow": 1, "goodRateShow": 98, "goodRateStyle": 147, "skuIds": null, "generalRateShow": 1, "generalRate": 0.012, "skuId": 2985018, "poorRateStyle": 1, "goodCount": 300, "afterCountStr": "7", "poorCount": 3, "commentCountStr": "300+", "showCount": 200, "generalCount": 4, "generalCountStr": "4", "showCountStr": "200+", "productId": 2985018}, "jwotestProduct": "99", "maxPage": 32, "score": 0, "imageListCount": 500}}
{"maxPage": 46, "referenceId": "2323565", "summary": {"soType": 5, "productAttr": null, "productCommentSummary": {"poorCountStr": "6", "averageScore": 5, "commentCount": 400, "goodRate": 0.972, "goodCountStr": "400+", "generalRateStyle": 2, "afterCount": 1, "poorRate": 0.013, "poorRateShow": 1, "goodRateShow": 97, "goodRateStyle": 146, "skuIds": null, "generalRateShow": 2, "generalRate": 0.015, "skuId": 2323565, "poorRateStyle": 2, "goodCount": 400, "afterCountStr": "1", "poorCount": 6, "commentCountStr": "400+", "showCount": 50, "generalCount": 7, "generalCountStr": "7", "showCountStr": "50+", "productId": 2323565}, "jwotestProduct": "99", "maxPage": 46, "score": 0, "imageListCount": 136}}
{"maxPage": 449, "referenceId": "1015658", "summary": {"soType": 5, "productAttr": null, "productCommentSummary": {"poorCountStr": "90+", "averageScore": 5, "commentCount": 4400, "goodRate": 0.948, "goodCountStr": "4200+", "generalRateStyle": 5, "afterCount": 1, "poorRate": 0.022, "poorRateShow": 2, "goodRateShow": 95, "goodRateStyle": 142, "skuIds": null, "generalRateShow": 3, "generalRate": 0.03, "skuId": 1015658, "poorRateStyle": 3, "goodCount": 4200, "afterCountStr": "1", "poorCount": 90, "commentCountStr": "4400+", "showCount": 800, "generalCount": 100, "generalCountStr": "100+", "showCountStr": "800+", "productId": 1015658}, "jwotestProduct": "99", "maxPage": 449, "score": 0, "imageListCount": 500}}
{"maxPage": 5, "referenceId": "3130037", "summary": {"soType": 5, "productAttr": null, "productCommentSummary": {"poorCountStr": "3", "averageScore": 5, "commentCount": 40, "goodRate": 0.91, "goodCountStr": "40+", "generalRateStyle": 3, "afterCount": 2, "poorRate": 0.068, "poorRateShow": 7, "goodRateShow": 91, "goodRateStyle": 137, "skuIds": null, "generalRateShow": 2, "generalRate": 0.022, "skuId": 3130037, "poorRateStyle": 10, "goodCount": 40, "afterCountStr": "2", "poorCount": 3, "commentCountStr": "40+", "showCount": 3, "generalCount": 1, "generalCountStr": "1", "showCountStr": "3", "productId": 3130037}, "jwotestProduct": "99", "maxPage": 5, "score": 0, "imageListCount": 5}}
{"maxPage": 13, "referenceId": "10883855679", "summary": {"soType": 5, "productAttr": null, "productCommentSummary": {"poorCountStr": "4", "averageScore": 5, "commentCount": 100, "goodRate": 0.938, "goodCountStr": "100+", "generalRateStyle": 5, "afterCount": 4, "poorRate": 0.031, "poorRateShow": 3, "goodRateShow": 94, "goodRateStyle": 140, "skuIds": null, "generalRateShow": 3, "generalRate": 0.031, "skuId": 10883855679, "poorRateStyle": 5, "goodCount": 100, "afterCountStr": "4", "poorCount": 4, "commentCountStr": "100+", "showCount": 30, "generalCount": 4, "generalCountStr": "4", "showCountStr": "30+", "productId": 10883855679}, "jwotestProduct": "99", "maxPage": 13, "score": 0, "imageListCount": 86}}
{"maxPage": 87, "referenceId": "1015600", "summary": {"soType": 5, "productAttr": null, "productCommentSummary": {"poorCountStr": "20+", "averageScore": 5, "commentCount": 800, "goodRate": 0.946, "goodCountStr": "800+", "generalRateStyle": 4, "afterCount": 0, "poorRate": 0.029, "poorRateShow": 3, "goodRateShow": 94, "goodRateStyle": 142, "skuIds": null, "generalRateShow": 3, "generalRate": 0.025, "skuId": 1015600, "poorRateStyle": 4, "goodCount": 800, "afterCountStr": "0", "poorCount": 20, "commentCountStr": "800+", "showCount": 100, "generalCount": 20, "generalCountStr": "20+", "showCountStr": "100+", "productId": 1015600}, "jwotestProduct": "99", "maxPage": 87, "score": 0, "imageListCount": 264}}
{"maxPage": 27, "referenceId": "1546467", "summary": {"soType": 5, "productAttr": null, "productCommentSummary": {"poorCountStr": "4", "averageScore": 5, "commentCount": 200, "goodRate": 0.964, "goodCountStr": "200+", "generalRateStyle": 3, "afterCount": 0, "poorRate": 0.014, "poorRateShow": 1, "goodRateShow": 97, "goodRateStyle": 145, "skuIds": null, "generalRateShow": 2, "generalRate": 0.022, "skuId": 1546467, "poorRateStyle": 2, "goodCount": 200, "afterCountStr": "0", "poorCount": 4, "commentCountStr": "200+", "showCount": 40, "generalCount": 6, "generalCountStr": "6", "showCountStr": "40+", "productId": 1546467}, "jwotestProduct": "99", "maxPage": 27, "score": 0, "imageListCount": 80}}
{"maxPage": 2, "referenceId": "10927130985", "summary": {"soType": 5, "productAttr": null, "productCommentSummary": {"poorCountStr": "0", "averageScore": 5, "commentCount": 10, "goodRate": 0.929, "goodCountStr": "10+", "generalRateStyle": 11, "afterCount": 0, "poorRate": 0.0, "poorRateShow": 0, "goodRateShow": 93, "goodRateStyle": 139, "skuIds": null, "generalRateShow": 7, "generalRate": 0.071, "skuId": 10927130985, "poorRateStyle": 0, "goodCount": 10, "afterCountStr": "0", "poorCount": 0, "commentCountStr": "10+", "showCount": 3, "generalCount": 1, "generalCountStr": "1", "showCountStr": "3", "productId": 10927130985}, "jwotestProduct": "99", "maxPage": 2, "score": 0, "imageListCount": 6}}
{"maxPage": 25, "referenceId": "1309864", "summary": {"soType": 5, "productAttr": null, "productCommentSummary": {"poorCountStr": "6", "averageScore": 5, "commentCount": 200, "goodRate": 0.956, "goodCountStr": "200+", "generalRateStyle": 3, "afterCount": 0, "poorRate": 0.024, "poorRateShow": 2, "goodRateShow": 96, "goodRateStyle": 143, "skuIds": null, "generalRateShow": 2, "generalRate": 0.02, "skuId": 1309864, "poorRateStyle": 4, "goodCount": 200, "afterCountStr": "0", "poorCount": 6, "commentCountStr": "200+", "showCount": 60, "generalCount": 5, "generalCountStr": "5", "showCountStr": "60+", "productId": 1309864}, "jwotestProduct": "99", "maxPage": 25, "score": 0, "imageListCount": 179}}
{"maxPage": 617, "referenceId": "1015577", "summary": {"soType": 5, "productAttr": null, "productCommentSummary": {"poorCountStr": "90+", "averageScore": 5, "commentCount": 6100, "goodRate": 0.955, "goodCountStr": "5800+", "generalRateStyle": 4, "afterCount": 0, "poorRate": 0.016, "poorRateShow": 2, "goodRateShow": 95, "goodRateStyle": 144, "skuIds": null, "generalRateShow": 3, "generalRate": 0.029, "skuId": 1015577, "poorRateStyle": 2, "goodCount": 5800, "afterCountStr": "0", "poorCount": 90, "commentCountStr": "6100+", "showCount": 300, "generalCount": 100, "generalCountStr": "100+", "showCountStr": "300+", "productId": 1015577}, "jwotestProduct": "99", "maxPage": 617, "score": 0, "imageListCount": 500}}
{"maxPage": 112, "referenceId": "1479005", "summary": {"soType": 5, "productAttr": null, "productCommentSummary": {"poorCountStr": "10+", "averageScore": 5, "commentCount": 1100, "goodRate": 0.959, "goodCountStr": "1000+", "generalRateStyle": 4, "afterCount": 0, "poorRate": 0.014, "poorRateShow": 1, "goodRateShow": 96, "goodRateStyle": 144, "skuIds": null, "generalRateShow": 3, "generalRate": 0.027, "skuId": 1479005, "poorRateStyle": 2, "goodCount": 1000, "afterCountStr": "0", "poorCount": 10, "commentCountStr": "1100+", "showCount": 200, "generalCount": 30, "generalCountStr": "30+", "showCountStr": "200+", "productId": 1479005}, "jwotestProduct": "99", "maxPage": 112, "score": 0, "imageListCount": 500}}
{"maxPage": 1621, "referenceId": "1015650", "summary": {"soType": 5, "productAttr": null, "productCommentSummary": {"poorCountStr": "300+", "averageScore": 5, "commentCount": 16000, "goodRate": 0.949, "goodCountStr": "1.5万+", "generalRateStyle": 4, "afterCount": 0, "poorRate": 0.022, "poorRateShow": 2, "goodRateShow": 95, "goodRateStyle": 143, "skuIds": null, "generalRateShow": 3, "generalRate": 0.029, "skuId": 1015650, "poorRateStyle": 3, "goodCount": 15000, "afterCountStr": "0", "poorCount": 300, "commentCountStr": "1.6万+", "showCount": 800, "generalCount": 400, "generalCountStr": "400+", "showCountStr": "800+", "productId": 1015650}, "jwotestProduct": "99", "maxPage": 1621, "score": 0, "imageListCount": 500}}
{"maxPage": 42, "referenceId": "1204719", "summary": {"soType": 5, "productAttr": null, "productCommentSummary": {"poorCountStr": "10+", "averageScore": 5, "commentCount": 400, "goodRate": 0.91, "goodCountStr": "300+", "generalRateStyle": 7, "afterCount": 0, "poorRate": 0.045, "poorRateShow": 5, "goodRateShow": 90, "goodRateStyle": 136, "skuIds": null, "generalRateShow": 5, "generalRate": 0.045, "skuId": 1204719, "poorRateStyle": 7, "goodCount": 300, "afterCountStr": "0", "poorCount": 10, "commentCountStr": "400+", "showCount": 30, "generalCount": 10, "generalCountStr": "10+", "showCountStr": "30+", "productId": 1204719}, "jwotestProduct": "99", "maxPage": 42, "score": 0, "imageListCount": 81}}
{"maxPage": 37, "referenceId": "1546453", "summary": {"soType": 5, "productAttr": null, "productCommentSummary": {"poorCountStr": "3", "averageScore": 5, "commentCount": 300, "goodRate": 0.974, "goodCountStr": "300+", "generalRateStyle": 3, "afterCount": 0, "poorRate": 0.008, "poorRateShow": 1, "goodRateShow": 97, "goodRateStyle": 146, "skuIds": null, "generalRateShow": 2, "generalRate": 0.018, "skuId": 1546453, "poorRateStyle": 1, "goodCount": 300, "afterCountStr": "0", "poorCount": 3, "commentCountStr": "300+", "showCount": 70, "generalCount": 7, "generalCountStr": "7", "showCountStr": "70+", "productId": 1546453}, "jwotestProduct": "99", "maxPage": 37, "score": 0, "imageListCount": 152}}
{"maxPage": 5771, "referenceId": "1069487", "summary": {"soType": 5, "productAttr": null, "productCommentSummary": {"poorCountStr": "900+", "averageScore": 5, "commentCount": 57000, "goodRate": 0.96, "goodCountStr": "5.5万+", "generalRateStyle": 3, "afterCount": 0, "poorRate": 0.017, "poorRateShow": 2, "goodRateShow": 96, "goodRateStyle": 144, "skuIds": null, "generalRateShow": 2, "generalRate": 0.023, "skuId": 1069487, "poorRateStyle": 3, "goodCount": 55000, "afterCountStr": "0", "poorCount": 900, "commentCountStr": "5.7万+", "showCount": 3100, "generalCount": 1300, "generalCountStr": "1300+", "showCountStr": "3100+", "productId": 1069487}, "jwotestProduct": "99", "maxPage": 5771, "score": 0, "imageListCount": 500}}
{"maxPage": 109, "referenceId": "1204720", "summary": {"soType": 5, "productAttr": null, "productCommentSummary": {"poorCountStr": "20+", "averageScore": 5, "commentCount": 1000, "goodRate": 0.965, "goodCountStr": "1000+", "generalRateStyle": 2, "afterCount": 0, "poorRate": 0.02, "poorRateShow": 2, "goodRateShow": 96, "goodRateStyle": 145, "skuIds": null, "generalRateShow": 2, "generalRate": 0.015, "skuId": 1204720, "poorRateStyle": 3, "goodCount": 1000, "afterCountStr": "0", "poorCount": 20, "commentCountStr": "1000+", "showCount": 200, "generalCount": 10, "generalCountStr": "10+", "showCountStr": "200+", "productId": 1204720}, "jwotestProduct": "99", "maxPage": 109, "score": 0, "imageListCount": 500}}
{"maxPage": 131, "referenceId": "1703810", "summary": {"soType": 5, "productAttr": null, "productCommentSummary": {"poorCountStr": "20+", "averageScore": 5, "commentCount": 1300, "goodRate": 0.954, "goodCountStr": "1200+", "generalRateStyle": 4, "afterCount": 1, "poorRate": 0.018, "poorRateShow": 2, "goodRateShow": 95, "goodRateStyle": 143, "skuIds": null, "generalRateShow": 3, "generalRate": 0.028, "skuId": 1703810, "poorRateStyle": 3, "goodCount": 1200, "afterCountStr": "1", "poorCount": 20, "commentCountStr": "1300+", "showCount": 100, "generalCount": 30, "generalCountStr": "30+", "showCountStr": "100+", "productId": 1703810}, "jwotestProduct": "99", "maxPage": 131, "score": 0, "imageListCount": 405}}
{"maxPage": 16, "referenceId": "3389147", "summary": {"soType": 5, "productAttr": null, "productCommentSummary": {"poorCountStr": "2", "averageScore": 5, "commentCount": 100, "goodRate": 0.976, "goodCountStr": "100+", "generalRateStyle": 2, "afterCount": 9, "poorRate": 0.012, "poorRateShow": 1, "goodRateShow": 98, "goodRateStyle": 146, "skuIds": null, "generalRateShow": 1, "generalRate": 0.012, "skuId": 3389147, "poorRateStyle": 2, "goodCount": 100, "afterCountStr": "9", "poorCount": 2, "commentCountStr": "100+", "showCount": 80, "generalCount": 2, "generalCountStr": "2", "showCountStr": "80+", "productId": 3389147}, "jwotestProduct": "99", "maxPage": 16, "score": 0, "imageListCount": 290}}
{"maxPage": 312, "referenceId": "1479019", "summary": {"soType": 5, "productAttr": null, "productCommentSummary": {"poorCountStr": "50+", "averageScore": 5, "commentCount": 3100, "goodRate": 0.967, "goodCountStr": "3000+", "generalRateStyle": 2, "afterCount": 5, "poorRate": 0.017, "poorRateShow": 2, "goodRateShow": 96, "goodRateStyle": 145, "skuIds": null, "generalRateShow": 2, "generalRate": 0.016, "skuId": 1479019, "poorRateStyle": 3, "goodCount": 3000, "afterCountStr": "5", "poorCount": 50, "commentCountStr": "3100+", "showCount": 900, "generalCount": 50, "generalCountStr": "50+", "showCountStr": "900+", "productId": 1479019}, "jwotestProduct": "99", "maxPage": 312, "score": 0, "imageListCount": 500}}
